mano/__init__.py
mano/__version__.py
mano/config.json
mano/sync/__init__.py
mano-0.5.2.dist-info/LICENSE
mano-0.5.2.dist-info/METADATA
mano-0.5.2.dist-info/WHEEL
mano-0.5.2.dist-info/top_level.txt
mano-0.5.2.dist-info/RECORD
