Metadata-Version: 2.1
Name: mano
Version: 0.5.2
Summary: Python API for Beiwe Research Platform
Home-page: https://www.neuroinfo.org
Author: Neuroinformatics Research Group
Author-email: info@neuroinfo.org
License-File: LICENSE
Requires-Dist: requests
Requires-Dist: lxml
Requires-Dist: python-dateutil
Requires-Dist: cryptease
